synapse_invite_checker/__init__.py
synapse_invite_checker/config.py
synapse_invite_checker/invite_checker.py
synapse_invite_checker/permissions.py
synapse_invite_checker/types.py
synapse_invite_checker/rest/__init__.py
synapse_invite_checker/rest/base.py
synapse_invite_checker/rest/messenger_info.py
synapse_invite_checker-0.4.13.dist-info/METADATA
synapse_invite_checker-0.4.13.dist-info/WHEEL
synapse_invite_checker-0.4.13.dist-info/licenses/LICENSE
synapse_invite_checker-0.4.13.dist-info/RECORD
