Metadata-Version: 2.4
Name: synapse-invite-checker
Version: 0.4.13
Summary: Synapse module to handle TIM contact management and invite permissions
Project-URL: Documentation, https://github.com/famedly/synapse-invite-checker#synapse-invite-checker
Project-URL: Issues, https://github.com/famedly/synapse-invite-checker/-/issues
Project-URL: Source, https://github.com/famedly/synapse-invite-checker/
Author-email: Nicolas Werner <n.werner@famedly.com>
License-Expression: AGPL-3.0-only
License-File: LICENSE
Classifier: Development Status :: 4 - Beta
Classifier: Programming Language :: Python
Classifier: Programming Language :: Python :: 3.11
Classifier: Programming Language :: Python :: 3.12
Classifier: Programming Language :: Python :: Implementation :: CPython
Classifier: Programming Language :: Python :: Implementation :: PyPy
Requires-Python: >=3.11
Requires-Dist: asyncache
Requires-Dist: cachetools
Requires-Dist: emoji
Requires-Dist: jwcrypto
Requires-Dist: pyopenssl
Requires-Dist: twisted
